concon.py
concon-2.0.1.dist-info/DESCRIPTION.rst
concon-2.0.1.dist-info/METADATA
concon-2.0.1.dist-info/RECORD
concon-2.0.1.dist-info/WHEEL
concon-2.0.1.dist-info/metadata.json
concon-2.0.1.dist-info/top_level.txt
