Metadata-Version: 2.0
Name: concon
Version: 2.0.1
Summary: CONstrained CONtainers: immutable & append-only containers.
Home-page: https://github.com/nejucomo/concon
Author: Nathan Wilcox
Author-email: nejucomo@gmail.com
License: MIT (see LICENSE.txt)
Platform: UNKNOWN
